matterlab_relays/__init__.py
matterlab_relays/base_relay.py
matterlab_relays/cer221a_relay.py
matterlab_relays/jydao_relay.py
matterlab_relays/r421b16_relay.py
matterlab_relays-1.0.4.dist-info/licenses/LICENSE
matterlab_relays-1.0.4.dist-info/METADATA
matterlab_relays-1.0.4.dist-info/WHEEL
matterlab_relays-1.0.4.dist-info/entry_points.txt
matterlab_relays-1.0.4.dist-info/top_level.txt
matterlab_relays-1.0.4.dist-info/RECORD
